odoo8_addon_l10n_es_aeat_mod303_oss-8.0.1.0.0.99.dev4-py3.8-nspkg.pth
odoo_addons/l10n_es_aeat_mod303_oss/README.rst
odoo_addons/l10n_es_aeat_mod303_oss/__init__.py
odoo_addons/l10n_es_aeat_mod303_oss/__openerp__.py
odoo_addons/l10n_es_aeat_mod303_oss/data/tax_code_map_mod303_data.xml
odoo_addons/l10n_es_aeat_mod303_oss/i18n/l10n_es_aeat_mod303_oss.pot
odoo_addons/l10n_es_aeat_mod303_oss/models/__init__.py
odoo_addons/l10n_es_aeat_mod303_oss/models/mod303.py
odoo_addons/l10n_es_aeat_mod303_oss/readme/CONTRIBUTORS.rst
odoo_addons/l10n_es_aeat_mod303_oss/readme/DESCRIPTION.rst
odoo_addons/l10n_es_aeat_mod303_oss/static/description/icon.png
odoo_addons/l10n_es_aeat_mod303_oss/static/description/icon_source.svg
odoo_addons/l10n_es_aeat_mod303_oss/static/description/index.html
odoo8_addon_l10n_es_aeat_mod303_oss-8.0.1.0.0.99.dev4.dist-info/METADATA
odoo8_addon_l10n_es_aeat_mod303_oss-8.0.1.0.0.99.dev4.dist-info/WHEEL
odoo8_addon_l10n_es_aeat_mod303_oss-8.0.1.0.0.99.dev4.dist-info/namespace_packages.txt
odoo8_addon_l10n_es_aeat_mod303_oss-8.0.1.0.0.99.dev4.dist-info/top_level.txt
odoo8_addon_l10n_es_aeat_mod303_oss-8.0.1.0.0.99.dev4.dist-info/RECORD
